galaxyxml/__init__.py
galaxyxml/tool/__init__.py
galaxyxml/tool/import_xml.py
galaxyxml/tool/parameters/__init__.py
galaxyxmlfubar/__init__.py
galaxyxmlfubar/tool/__init__.py
galaxyxmlfubar/tool/import_xml.py
galaxyxmlfubar/tool/parameters/__init__.py
galaxyxmlfubar-0.4.16.data/data/LICENSE.TXT
galaxyxmlfubar-0.4.16.dist-info/LICENSE.TXT
galaxyxmlfubar-0.4.16.dist-info/METADATA
galaxyxmlfubar-0.4.16.dist-info/WHEEL
galaxyxmlfubar-0.4.16.dist-info/top_level.txt
galaxyxmlfubar-0.4.16.dist-info/RECORD
