Metadata-Version: 2.1
Name: galaxyxmlfubar
Version: 0.4.16
Summary: Galaxy XML generation library fork
Home-page: UNKNOWN
Author: Ross Lazarus
Author-email: oldf4rt@hotmail.com
License: UNKNOWN
Platform: UNKNOWN
Classifier: Development Status :: 4 - Beta
Classifier: Operating System :: OS Independent
Classifier: Intended Audience :: Developers
Classifier: Environment :: Console
Classifier: License :: OSI Approved :: Apache Software License
License-File: LICENSE.TXT
Requires-Dist: galaxy-tool-util
Requires-Dist: lxml
